MANIFEST.in
README.md
setup.py
MVGLive/__init__.py
MVGLive/mvglive.py
PyMVGLive.egg-info/PKG-INFO
PyMVGLive.egg-info/SOURCES.txt
PyMVGLive.egg-info/dependency_links.txt
PyMVGLive.egg-info/requires.txt
PyMVGLive.egg-info/top_level.txt