Metadata-Version: 1.1
Name: PyMVGLive
Version: 1.1.1
Summary: get live-data from mvg-live.de
Home-page: https://github.com/pc-coholic/PyMVGLive
Author: pc-coholic
Author-email: martin@pc-coholic.de
License: ?
Platform: UNKNOWN
Classifier: Programming Language :: Python :: 2
Classifier: Programming Language :: Python :: 3
Classifier: Intended Audience :: Developers
Classifier: Topic :: Software Development :: Libraries :: Python Modules
